heuf/__init__.py
heuf/dir/__init__.py
heuf/file/__init__.py
heuf/file/import_dict/__init__.py
heuf/rsc/__init__.py
heuf/rsc/dir/__init__.py
heuf/rsc/dir/basename.py
heuf/rsc/dir/copy.py
heuf/rsc/dir/create.py
heuf/rsc/dir/is_creatable.py
heuf/rsc/dir/is_exists.py
heuf/rsc/dir/is_readable.py
heuf/rsc/dir/is_writable.py
heuf/rsc/dir/sir_dir_path.py
heuf/rsc/dir/sub_dir_names.py
heuf/rsc/dir/sub_dir_paths.py
heuf/rsc/dir/sub_file_names.py
heuf/rsc/dir/sub_file_paths.py
heuf/rsc/dir/sub_names.py
heuf/rsc/dir/sub_path.py
heuf/rsc/dir/sub_paths.py
heuf/rsc/file/__init__.py
heuf/rsc/file/append.py
heuf/rsc/file/basename.py
heuf/rsc/file/copy.py
heuf/rsc/file/is_creatable.py
heuf/rsc/file/is_exists.py
heuf/rsc/file/is_readable.py
heuf/rsc/file/is_writable.py
heuf/rsc/file/sir_dir_path.py
heuf/rsc/file/write.py
heuf/rsc/file/import_dict/__init__.py
heuf/rsc/file/import_dict/from_ini_file.py
heuf/rsc/file/import_dict/from_py_file.py
heuf-1.1.8.dist-info/LICENSE.rst
heuf-1.1.8.dist-info/METADATA
heuf-1.1.8.dist-info/WHEEL
heuf-1.1.8.dist-info/top_level.txt
heuf-1.1.8.dist-info/RECORD
