Metadata-Version: 2.1
Name: heuf
Version: 1.1.8
Summary: Python Utilities Functions
Home-page: https://py.hebill.net/heuf
Author: He Bill
Author-email: hebill@me.com
Requires-Python: >=3.12
License-File: LICENSE.rst
